translatable_xblocks/__init__.py
translatable_xblocks/ai_translations_service.py
translatable_xblocks/apps.py
translatable_xblocks/base.py
translatable_xblocks/config.py
translatable_xblocks/fields.py
translatable_xblocks/filters.py
translatable_xblocks/platform_imports.py
translatable_xblocks/test_fields.py
translatable_xblocks/utils.py
translatable_xblocks/api/__init__.py
translatable_xblocks/api/urls.py
translatable_xblocks/api/utils.py
translatable_xblocks/api/views.py
translatable_xblocks/settings/__init__.py
translatable_xblocks/settings/common.py
translatable_xblocks/settings/devstack.py
translatable_xblocks/settings/production.py
translatable_xblocks/xblocks/__init__.py
translatable_xblocks/xblocks/capa_block.py
translatable_xblocks/xblocks/html_block.py
translatable_xblocks/xblocks/poll_block.py
translatable_xblocks/xblocks/video_block.py
translatable_xblocks-1.6.2.dist-info/licenses/LICENSE
translatable_xblocks-1.6.2.dist-info/licenses/LICENSE.txt
translatable_xblocks-1.6.2.dist-info/METADATA
translatable_xblocks-1.6.2.dist-info/WHEEL
translatable_xblocks-1.6.2.dist-info/entry_points.txt
translatable_xblocks-1.6.2.dist-info/top_level.txt
translatable_xblocks-1.6.2.dist-info/RECORD
