Metadata-Version: 2.4
Name: translatable-xblocks
Version: 1.6.2
Summary: Plugin for adding translation behavior to XBlocks
Home-page: https://github.com/edx/translatable-xblocks
Author: Nathan Sprenkle
Author-email: nsprenkle@2u.org
License: AGPL-3.0-or-later
Keywords: Python edx
Classifier: Development Status :: 3 - Alpha
Classifier: Framework :: Django
Classifier: Framework :: Django :: 4.2
Classifier: Intended Audience :: Developers
Classifier: Natural Language :: English
Classifier: Programming Language :: Python :: 3
Classifier: Programming Language :: Python :: 3.11
Requires-Python: >=3.11
License-File: LICENSE
License-File: LICENSE.txt
Requires-Dist: Django
Requires-Dist: django-oauth-toolkit
Requires-Dist: djangorestframework
Requires-Dist: edx-opaque-keys
Requires-Dist: edx-rest-api-client
Requires-Dist: edx_django_utils
Requires-Dist: openedx-atlas
Requires-Dist: openedx-filters
Requires-Dist: xblock>=5.1.0
Dynamic: author
Dynamic: author-email
Dynamic: classifier
Dynamic: description
Dynamic: home-page
Dynamic: keywords
Dynamic: license
Dynamic: license-file
Dynamic: requires-dist
Dynamic: requires-python
Dynamic: summary
